torchmojiartifact/TorchmojiModelArtifact.py
torchmojiartifact/__init__.py
torchmojiartifact-0.0.4.dist-info/METADATA
torchmojiartifact-0.0.4.dist-info/WHEEL
torchmojiartifact-0.0.4.dist-info/top_level.txt
torchmojiartifact-0.0.4.dist-info/RECORD
