Metadata-Version: 2.1
Name: torchmojiartifact
Version: 0.0.4
Summary: BentoML artifact framework for the Torchmoji Model
Home-page: https://github.com/markmo/torchmojiartifact
Author: Mark Moloney
Author-email: m4rkmo@gmail.com
License: UNKNOWN
Platform: UNKNOWN
Classifier: Programming Language :: Python :: 3
Classifier: License :: OSI Approved :: MIT License
Classifier: Operating System :: OS Independent
Requires-Python: >=3.6
Requires-Dist: BentoML (==0.10.1)
